{"note":"This file is an internal implementation detail to speed up HTML report generation. Its format can change at any time. You might be looking for the JSON report: https://coverage.rtfd.io/cmd.html#cmd-json","format":5,"version":"7.5.3","globals":"f0f993e0be87960117d582fe5657c1d7","files":{"script_py":{"hash":"40ec1234738c08c7ba5f8c299bb3d3c4","index":{"url":"script_py.html","file":"script.py","description":"","nums":{"precision":0,"n_files":1,"n_statements":3,"n_excluded":0,"n_missing":3,"n_branches":0,"n_partial_branches":0,"n_missing_branches":0}}},"z_d2a0bc3e699ec5e2_spider_py":{"hash":"9d44eb6f669e109dbfb2804d553d1fe9","index":{"url":"z_d2a0bc3e699ec5e2_spider_py.html","file":"src/tiny_web_crawler/core/spider.py","description":"","nums":{"precision":0,"n_files":1,"n_statements":82,"n_excluded":0,"n_missing":0,"n_branches":0,"n_partial_branches":0,"n_missing_branches":0}}},"z_c1696ee00dbdb9e1_fetcher_py":{"hash":"678047f232a0b3729d95a80878b6357b","index":{"url":"z_c1696ee00dbdb9e1_fetcher_py.html","file":"src/tiny_web_crawler/networking/fetcher.py","description":"","nums":{"precision":0,"n_files":1,"n_statements":19,"n_excluded":0,"n_missing":0,"n_branches":0,"n_partial_branches":0,"n_missing_branches":0}}},"z_c1696ee00dbdb9e1_formatter_py":{"hash":"51b67c8a7273c47fb0ce4a316c010461","index":{"url":"z_c1696ee00dbdb9e1_formatter_py.html","file":"src/tiny_web_crawler/networking/formatter.py","description":"","nums":{"precision":0,"n_files":1,"n_statements":15,"n_excluded":0,"n_missing":0,"n_branches":0,"n_partial_branches":0,"n_missing_branches":0}}},"z_c1696ee00dbdb9e1_validator_py":{"hash":"628b90df1b353eeab026713c7ce26063","index":{"url":"z_c1696ee00dbdb9e1_validator_py.html","file":"src/tiny_web_crawler/networking/validator.py","description":"","nums":{"precision":0,"n_files":1,"n_statements":3,"n_excluded":0,"n_missing":0,"n_branches":0,"n_partial_branches":0,"n_missing_branches":0}}},"z_09fe4844d34b41d9_test_fetcher_py":{"hash":"febd146d854d1ee4733f3a9346ea7307","index":{"url":"z_09fe4844d34b41d9_test_fetcher_py.html","file":"tests/networking/test_fetcher.py","description":"","nums":{"precision":0,"n_files":1,"n_statements":39,"n_excluded":0,"n_missing":0,"n_branches":0,"n_partial_branches":0,"n_missing_branches":0}}},"z_09fe4844d34b41d9_test_formatter_py":{"hash":"b6879a321df2efccbee496505edd94d6","index":{"url":"z_09fe4844d34b41d9_test_formatter_py.html","file":"tests/networking/test_formatter.py","description":"","nums":{"precision":0,"n_files":1,"n_statements":7,"n_excluded":0,"n_missing":0,"n_branches":0,"n_partial_branches":0,"n_missing_branches":0}}},"z_09fe4844d34b41d9_test_validator_py":{"hash":"2677d388b460d1aa43c2a0aa711062ad","index":{"url":"z_09fe4844d34b41d9_test_validator_py.html","file":"tests/networking/test_validator.py","description":"","nums":{"precision":0,"n_files":1,"n_statements":4,"n_excluded":0,"n_missing":0,"n_branches":0,"n_partial_branches":0,"n_missing_branches":0}}},"z_a44f0ac069e85531_test_crawler_py":{"hash":"4b47549c7ea8760b61bdff7f387c3903","index":{"url":"z_a44f0ac069e85531_test_crawler_py.html","file":"tests/test_crawler.py","description":"","nums":{"precision":0,"n_files":1,"n_statements":100,"n_excluded":0,"n_missing":0,"n_branches":0,"n_partial_branches":0,"n_missing_branches":0}}},"z_a44f0ac069e85531_utils_py":{"hash":"ea2520c1af279e4e5d65bd047d74e481","index":{"url":"z_a44f0ac069e85531_utils_py.html","file":"tests/utils.py","description":"","nums":{"precision":0,"n_files":1,"n_statements":4,"n_excluded":0,"n_missing":0,"n_branches":0,"n_partial_branches":0,"n_missing_branches":0}}}}}